Metadata-Version: 2.4
Name: qdf2
Version: 0.0.1.7
Summary: 🚀Asynchronous based full-platform download tool
Project-URL: Homepage, https://github.com/Johnserf-Seed/f2
Project-URL: Documentation, https://f2.wiki/
Project-URL: Chat, https://discord.gg//3PhtPmgHf8
Project-URL: Source Code, https://github.com/Johnserf-Seed/f2
Project-URL: Issue Tracker, https://github.com/Johnserf-Seed/f2/issues
Author-email: Johnserf-Seed <support@f2.wiki>
License: Apache-2.0
License-File: LICENSE
Keywords: async,bark,bilibili,crawler,douyin,download,downloader,f2,http,http proxy,https,internat,netease,tiktok,twitter,watermark,websockets,weibo,ws,wss,x
Classifier: Development Status :: 4 - Beta
Classifier: Environment :: Console
Classifier: Environment :: Plugins
Classifier: Environment :: Web Environment
Classifier: Framework :: AsyncIO
Classifier: Intended Audience :: Customer Service
Classifier: Intended Audience :: Developers
Classifier: License :: OSI Approved :: Apache Software License
Classifier: Natural Language :: Chinese (Simplified)
Classifier: Natural Language :: English
Classifier: Operating System :: OS Independent
Classifier: Programming Language :: Python :: 3
Classifier: Programming Language :: Python :: 3 :: Only
Classifier: Programming Language :: Python :: 3.10
Classifier: Programming Language :: Python :: 3.11
Classifier: Topic :: Internet :: WWW/HTTP
Classifier: Topic :: Software Development :: Libraries
Classifier: Topic :: Software Development :: Libraries :: Python Modules
Classifier: Topic :: Utilities
Classifier: Typing :: Typed
Requires-Python: >=3.10
Requires-Dist: aiofiles==24.1.0
Requires-Dist: aiosqlite==0.20.0
Requires-Dist: babel==2.13.0
Requires-Dist: black==24.10.0
Requires-Dist: browser-cookie3==0.20.1
Requires-Dist: click==8.1.7
Requires-Dist: cryptography==44.0.1
Requires-Dist: gmssl==3.2.2
Requires-Dist: httpx==0.28.1
Requires-Dist: importlib-resources==6.4.5
Requires-Dist: jsonpath-ng==1.6.1
Requires-Dist: m3u8==3.6.0
Requires-Dist: protobuf==5.28.3
Requires-Dist: pydantic==2.9.*
Requires-Dist: pyexecjs==1.5.1
Requires-Dist: pytest-asyncio==0.25.0
Requires-Dist: pytest==8.3.4
Requires-Dist: pyyaml==6.0.2
Requires-Dist: qrcode==8.0
Requires-Dist: rich==13.9.3
Requires-Dist: websockets-proxy==0.1.2
Requires-Dist: websockets<13.0
